first_step/.DS_Store
first_step/__init__.py
first_step/cli.py
first_step/increment.py
first_step-0.1.0.dist-info/entry_points.txt
first_step-0.1.0.dist-info/WHEEL
first_step-0.1.0.dist-info/METADATA
first_step-0.1.0.dist-info/RECORD
