Metadata-Version: 2.1
Name: first-step
Version: 0.1.0
Summary: 
Author: jasjung
Author-email: insikjung2017@u.northwestern.edu
Requires-Python: >=3.8,<4.0
Classifier: Programming Language :: Python :: 3
Classifier: Programming Language :: Python :: 3.10
Classifier: Programming Language :: Python :: 3.8
Classifier: Programming Language :: Python :: 3.9
Requires-Dist: click (>=8.0.4,<9.0.0)
